catomatic/BinaryCatalogue.py
catomatic/Ecoff.py
catomatic/PiezoTools.py
catomatic/RegressionCatalogue.py
catomatic/__init__.py
catomatic/__main__.py
catomatic/cli.py
catomatic/defence_module.py
catomatic-0.1.9.dist-info/LICENSE
catomatic-0.1.9.dist-info/METADATA
catomatic-0.1.9.dist-info/WHEEL
catomatic-0.1.9.dist-info/entry_points.txt
catomatic-0.1.9.dist-info/top_level.txt
catomatic-0.1.9.dist-info/RECORD
