Metadata-Version: 2.2
Name: catomatic
Version: 0.1.9
Summary: A tool for automatically building catalogues of antibiotic resistance-associated variants
Home-page: https://github.com/fowler-lab/catomatic
Author: Dylan Adlard, Philip W Fowler
Author-email: philip.fowler@ndm.ox.ac.uk
License: MIT
Keywords: resistance catalogue,tuberculosis,clinical microbiology
Classifier: Programming Language :: Python :: 3
Requires-Python: >=3.6
License-File: LICENSE
Requires-Dist: piezo
Requires-Dist: numpy
Requires-Dist: scipy
Requires-Dist: pandas
